{
  "id": "2011-12-26-trains-running-slower-due-to-speed-restrictions",
  "title": "Trains running slower due to speed restrictions",
  "title_translations": {
    "zh-Hans": "由于限速，火车运行速度较慢",
    "ms": "Kereta api berjalan lebih perlahan kerana sekatan kelajuan",
    "ta": "வேகக் கட்டுப்பாடுகள் காரணமாக ரயில்கள் மெதுவாக இயங்குகின்றன"
  },
  "startAt": "2011-12-26T10:48:38.000+08:00",
  "endAt": "2011-12-27T00:00:00.000+08:00",
  "type": "disruption",
  "subtypes": [
    "delay"
  ],
  "updates": [
    {
      "type": "operator.update",
      "text": "SVC UPDATE:NSEW lines are smooth but travelling slowly due to speed limits.",
      "sourceUrl": "https://x.com/SMRT_Singapore/status/151195999975649280",
      "createdAt": "2011-12-26T15:01:50.000+08:00"
    },
    {
      "type": "operator.update",
      "text": "Trains are running slower this morning due to speed restrictions.",
      "sourceUrl": "https://x.com/SMRT_Singapore/status/151132281954770944",
      "createdAt": "2011-12-26T10:48:38.000+08:00"
    }
  ],
  "stationIdsAffected": [
    {
      "branchName": "main",
      "stationIds": [
        "DBG",
        "CTH",
        "RFP",
        "AMK",
        "YCK",
        "KTB",
        "YIS",
        "SBW",
        "ADM",
        "WDL",
        "MSL",
        "KRJ",
        "YWT",
        "CCK",
        "BGB",
        "BBT",
        "JUR",
        "BSH",
        "BDL",
        "TAP",
        "NOV",
        "NEW",
        "ORC",
        "SOM",
        "MRB"
      ],
      "lineId": "NSL"
    },
    {
      "branchName": "main",
      "stationIds": [
        "JKN",
        "PNR",
        "BNL",
        "LKS",
        "CNG",
        "JUR",
        "CLE",
        "DVR",
        "BNV",
        "COM",
        "QUE",
        "RDH",
        "TIB",
        "OTP",
        "TPG",
        "RFP",
        "CTH",
        "BGS",
        "LVR",
        "KAL",
        "ALJ",
        "PYL",
        "EUN",
        "KEM",
        "BDK",
        "TNM",
        "SIM",
        "TAM",
        "PSR"
      ],
      "lineId": "EWL"
    },
    {
      "branchName": "changi_airport",
      "stationIds": [
        "TNM",
        "XPO",
        "CGA"
      ],
      "lineId": "EWL"
    }
  ],
  "lineIdsAffected": [
    "NSL",
    "EWL"
  ]
}
