{
  "id": "EUN",
  "name": "Eunos",
  "name_translations": {
    "zh-Hans": "友诺士",
    "ta": "யூனுஸ்"
  },
  "town": "Geylang",
  "town_translations": {
    "zh-Hans": "芽笼",
    "ms": "Geylang",
    "ta": "கெய்லாங்"
  },
  "landmarks": [
    "Singapore Post Centre",
    "Paya Lebar Square",
    "Geylang Serai Market"
  ],
  "landmarks_translations": {
    "zh-Hans": [
      "新加坡邮政中心",
      "边连胜广场",
      "芽笼士乃市场"
    ],
    "ms": [
      "Pusat Pos Singapura",
      "Paya Lebar Square",
      "Pasar Geylang Serai"
    ],
    "ta": [
      "சிங்கப்பூர் அஞ்சல் மையம்",
      "Paya Lebar Square",
      "கெய்லாங் சிறை சந்தை"
    ]
  },
  "geo": {
    "latitude": 1.3192,
    "longitude": 103.8959
  },
  "lineMembers": {
    "EWL": [
      {
        "code": "EW7",
        "startedAt": "1989-11-04",
        "structureType": "elevated"
      }
    ]
  }
}
