{
  "id": "JRW",
  "name": "Jurong West",
  "name_translations": {
    "zh-Hans": "裕廊西",
    "ta": "ஜூரோங் வெஸ்ட்"
  },
  "componentMembers": {
    "JRL": [
      {
        "code": "JS6",
        "startedAt": "2027-12-31",
        "structureType": "elevated"
      }
    ]
  },
  "town": "Jurong West",
  "town_translations": {
    "zh-Hans": "裕廊西",
    "ms": "Jurong Barat",
    "ta": "ஜூராங் மேற்கே"
  },
  "landmarks": [
    "Corporation Primary School",
    "Boon Lay Community Centre",
    "Boon Lay Shopping Centre"
  ],
  "landmarks_translations": {
    "zh-Hans": [
      "合作小学",
      "文礼社区中心",
      "文礼购物中心"
    ],
    "ms": [
      "Sekolah Rendah Corporation",
      "Pusat Komuniti Boon Lay",
      "Pusat Beli-belah Boon Lay"
    ],
    "ta": [
      "கார்ப்பரேஷன் பிரைமரி பள்ளி",
      "பூன் லே சமூக மையம்",
      "பூன் லே ஷாப்பிங் சென்டர்"
    ]
  },
  "geo": {
    "latitude": 1.349,
    "longitude": 103.706
  }
}
