{
  "id": "TPN",
  "name": "Tampines North",
  "name_translations": {
    "zh-Hans": "淡滨尼北",
    "ta": "தெம்பினிஸ் நார்த்"
  },
  "town": "Tampines",
  "town_translations": {
    "zh-Hans": "淡滨尼",
    "ms": "Tampines",
    "ta": "தாம் பினஸ்"
  },
  "landmarks": [
    "Tampines Mall",
    "Century Square",
    "Our Tampines Hub"
  ],
  "landmarks_translations": {
    "zh-Hans": [
      "淡滨尼购物中心",
      "世纪广场",
      "淡滨尼中心"
    ],
    "ms": [
      "Pusat Membeli-belah Tampines",
      "Century Square",
      "Our Tampines Hub"
    ],
    "ta": [
      "Tampines Mall",
      "Century Square",
      "Our Tampines Hub"
    ]
  },
  "geo": {
    "latitude": 1.3572,
    "longitude": 103.9352
  },
  "lineMembers": {
    "CRL": [
      {
        "code": "CR6",
        "startedAt": "2030-12-31",
        "structureType": "underground"
      }
    ]
  }
}