{
  "id": "CRQ",
  "name": {
    "en-SG": "Clarke Quay",
    "zh-Hans": "克拉码头",
    "ms": null,
    "ta": "கிளார்க் கீ"
  },
  "geo": {
    "latitude": 1.28826,
    "longitude": 103.846598
  },
  "stationCodes": [
    {
      "lineId": "NEL",
      "code": "NE5",
      "startedAt": "2003-06-20",
      "endedAt": null,
      "structureType": "underground"
    }
  ],
  "landmarkIds": [
    "clarke-quay-central",
    "fort-canning-park",
    "robertson-quay"
  ],
  "townId": "singapore-river",
  "firstLastTrain": {
    "services": [
      {
        "serviceId": "NEL_MAIN_N",
        "times": {
          "weekday": {
            "firstTrain": "05:51",
            "lastTrain": "00:02"
          },
          "saturday": {
            "firstTrain": "05:51",
            "lastTrain": "00:02"
          },
          "sunday_public_holiday": {
            "firstTrain": "06:11",
            "lastTrain": "00:02"
          }
        }
      },
      {
        "serviceId": "NEL_MAIN_S",
        "times": {
          "weekday": {
            "firstTrain": "06:08",
            "lastTrain": "23:55"
          },
          "saturday": {
            "firstTrain": "06:08",
            "lastTrain": "23:55"
          },
          "sunday_public_holiday": {
            "firstTrain": "06:28",
            "lastTrain": "23:55"
          }
        }
      }
    ]
  }
}
