{
  "id": "SHV",
  "name": {
    "en-SG": "South View",
    "zh-Hans": "南景",
    "ms": null,
    "ta": "சவுத் வியூ"
  },
  "geo": {
    "latitude": 1.380272,
    "longitude": 103.745283
  },
  "stationCodes": [
    {
      "lineId": "BPLRT",
      "code": "BP2",
      "startedAt": "1999-11-06T00:00:00Z",
      "endedAt": null,
      "structureType": "elevated"
    }
  ],
  "landmarkIds": [
    "bukit-panjang-plaza",
    "hillion-mall",
    "zhenghua-nature-park"
  ],
  "townId": "bukit-panjang"
}
