{
  "id": "2018-03-25-maintenance-sengkang-lrt",
  "title": "Maintenance work on Sengkang LRT system",
  "title_translations": {
    "zh-Hans": "盛港轻轨系统维修工作",
    "ms": "Kerja penyelenggaraan di sistem LRT Sengkang",
    "ta": "செங்காங் LRT அமைப்பில் பராமரிப்புப் பணி"
  },
  "startAt": "2018-03-25T00:00:00.000+08:00",
  "endAt": "2018-03-26T07:00:00.000+08:00",
  "type": "maintenance",
  "cancelledAt": null,
  "subtypes": [
    "track.work"
  ],
  "updates": [
    {
      "type": "planned",
      "text": "We will be conducting maintenance work on the Sengkang LRT system this Sunday, 25 March 2018. \n‍‍‍‍‍‍ ‍‍\nTrain service will be available as usual at all stations, but only in one direction. Service in the opposite direction will start at 7am. https://t.co/jTZCjIh5ef",
      "sourceUrl": "https://x.com/SBSTransit_Ltd/status/975526461258936320",
      "createdAt": "2018-03-19T08:16:47.000+08:00"
    }
  ],
  "stationIdsAffected": [
    {
      "branchName": "west",
      "stationIds": [
        "SKG",
        "CGL",
        "FMW",
        "KPG",
        "TNG",
        "FNV",
        "LYR",
        "TKG",
        "RNJ"
      ],
      "lineId": "SKLRT"
    },
    {
      "branchName": "east",
      "stationIds": [
        "SKG",
        "CPV",
        "RMB",
        "BAK",
        "KGK",
        "RNG"
      ],
      "lineId": "SKLRT"
    }
  ],
  "lineIdsAffected": [
    "SKLRT"
  ],
  "rrule": null
}